[
  {
    "icon": {
      "glyph": {
        "code": "u27B0",
        "name": "curlyloop"
      },
      "layers": [
        {
          "color": "2B3B47",
          "name": "u27B0.layer1",
          "order": 1
        }
      ]
    }
  },
  {
    "icon": {
      "glyph": {
        "code": "u303D",
        "name": "partalternationmark"
      },
      "layers": [
        {
          "color": "FFB636",
          "name": "u303D.layer1",
          "order": 1
        }
      ]
    }
  },
  {
    "icon": {
      "glyph": {
        "code": "u2B05",
        "name": "leftwardsblackarrow"
      },
      "layers": [
        {
          "color": "597B91",
          "name": "u2B05.layer1",
          "order": 1
        },
        {
          "color": "2B5770",
          "name": "u2B05.layer2",
          "order": 2
        },
        {
          "color": "F9F9F7",
          "name": "u2B05.layer3",
          "order": 3
        }
      ]
    }
  },
  {
    "icon": {
      "glyph": {
        "code": "u1F4AE",
        "name": "whiteflower"
      },
      "layers": [
        {
          "color": "FF473E",
          "name": "u1F4AE.layer1",
          "order": 1
        },
        {
          "color": "FF473E",
          "name": "u1F4AE.layer2",
          "order": 2
        }
      ]
    }
  },
  {
    "icon": {
      "glyph": {
        "code": "u1F4F5",
        "name": "nomobilephones"
      },
      "layers": [
        {
          "color": "8F9799",
          "name": "u1F4F5.layer1",
          "order": 1
        },
        {
          "color": "2B3B47",
          "name": "u1F4F5.layer2",
          "order": 2
        },
        {
          "color": "8F9799",
          "name": "u1F4F5.layer3",
          "order": 3
        },
        {
          "color": "FF473E",
          "name": "u1F4F5.layer4",
          "order": 4
        }
      ]
    }
  },
  {
    "icon": {
      "glyph": {
        "code": "u1F4F6",
        "name": "antennawithbars"
      },
      "layers": [
        {
          "color": "597B91",
          "name": "u1F4F6.layer1",
          "order": 1
        },
        {
          "color": "2B5770",
          "name": "u1F4F6.layer2",
          "order": 2
        },
        {
          "color": "FFFFFF",
          "name": "u1F4F6.layer3",
          "order": 3
        }
      ]
    }
  },
  {
    "icon": {
      "glyph": {
        "code": "u1F4AF",
        "name": "hundredpointssymbol"
      },
      "layers": [
        {
          "color": "FF473E",
          "name": "u1F4AF.layer1",
          "order": 1
        },
        {
          "color": "FF473E",
          "name": "u1F4AF.layer2",
          "order": 2
        },
        {
          "color": "FF473E",
          "name": "u1F4AF.layer3",
          "order": 3
        },
        {
          "color": "FF473E",
          "name": "u1F4AF.layer4",
          "order": 4
        },
        {
          "color": "FF473E",
          "name": "u1F4AF.layer5",
          "order": 5
        }
      ]
    }
  },
  {
    "icon": {
      "glyph": {
        "code": "u1F4F3",
        "name": "vibrationmode"
      },
      "layers": [
        {
          "color": "FFB636",
          "name": "u1F4F3.layer1",
          "order": 1
        },
        {
          "color": "ED9B43",
          "name": "u1F4F3.layer2",
          "order": 2
        },
        {
          "color": "FFFFFF",
          "name": "u1F4F3.layer3",
          "order": 3
        },
        {
          "color": "FFB636",
          "name": "u1F4F3.layer4",
          "order": 4
        },
        {
          "color": "FCB535",
          "name": "u1F4F3.layer5",
          "order": 5
        },
        {
          "color": "FFFFFF",
          "name": "u1F4F3.layer6",
          "order": 6
        }
      ]
    }
  },
  {
    "icon": {
      "glyph": {
        "code": "u1F4B1",
        "name": "currencyexchange"
      },
      "layers": [
        {
          "color": "2B3B47",
          "name": "u1F4B1.layer1",
          "order": 1
        },
        {
          "color": "2B3B47",
          "name": "u1F4B1.layer2",
          "order": 2
        },
        {
          "color": "2B3B47",
          "name": "u1F4B1.layer3",
          "order": 3
        },
        {
          "color": "2B3B47",
          "name": "u1F4B1.layer4",
          "order": 4
        }
      ]
    }
  },
  {
    "icon": {
      "glyph": {
        "code": "u1F4B2",
        "name": "heavydollarsign"
      },
      "layers": [
        {
          "color": "2B3B47",
          "name": "u1F4B2.layer1",
          "order": 1
        }
      ]
    }
  },
  {
    "icon": {
      "glyph": {
        "code": "u1F6B9",
        "name": "menssymbol"
      },
      "layers": [
        {
          "color": "00B1FF",
          "name": "u1F6B9.layer1",
          "order": 1
        },
        {
          "color": "0096D1",
          "name": "u1F6B9.layer2",
          "order": 2
        },
        {
          "color": "FFFFFF",
          "name": "u1F6B9.layer3",
          "order": 3
        }
      ]
    }
  },
  {
    "icon": {
      "glyph": {
        "code": "u1F6AF",
        "name": "donotlittersymbol"
      },
      "layers": [
        {
          "color": "2B3B47",
          "name": "u1F6AF.layer0",
          "order": 0
        },
        {
          "color": "2B3B47",
          "name": "u1F6AF.layer1",
          "order": 1
        },
        {
          "color": "FF473E",
          "name": "u1F6AF.layer2",
          "order": 2
        },
        {
          "color": "FF473E",
          "name": "u1F6AF.layer3",
          "order": 3
        }
      ]
    }
  },
  {
    "icon": {
      "glyph": {
        "code": "u1F6AE",
        "name": "putlitterinitsplacesymbol"
      },
      "layers": [
        {
          "color": "597B91",
          "name": "u1F6AE.layer1",
          "order": 1
        },
        {
          "color": "2B5770",
          "name": "u1F6AE.layer2",
          "order": 2
        },
        {
          "color": "FFFFFF",
          "name": "u1F6AE.layer3",
          "order": 3
        }
      ]
    }
  },
  {
    "icon": {
      "glyph": {
        "code": "u1F6AD",
        "name": "nosmokingsymbol"
      },
      "layers": [
        {
          "color": "00B1FF",
          "name": "u1F6AD.layer1",
          "order": 1
        },
        {
          "color": "0096D1",
          "name": "u1F6AD.layer2",
          "order": 2
        },
        {
          "color": "FFFFFF",
          "name": "u1F6AD.layer3",
          "order": 3
        }
      ]
    }
  },
  {
    "icon": {
      "glyph": {
        "code": "u1F4B9",
        "name": "chartupwardstrendyen"
      },
      "layers": [
        {
          "color": "00B89C",
          "name": "u1F4B9.layer1",
          "order": 1
        },
        {
          "color": "009E83",
          "name": "u1F4B9.layer2",
          "order": 2
        },
        {
          "color": "FFFFFF",
          "name": "u1F4B9.layer3",
          "order": 3
        },
        {
          "color": "FFFFFF",
          "name": "u1F4B9.layer4",
          "order": 4
        }
      ]
    }
  },
  {
    "icon": {
      "glyph": {
        "code": "u1F6B0",
        "name": "potablewatersystem"
      },
      "layers": [
        {
          "color": "00B1FF",
          "name": "u1F6B0.layer1",
          "order": 1
        },
        {
          "color": "0096D1",
          "name": "u1F6B0.layer2",
          "order": 2
        },
        {
          "color": "FFFFFF",
          "name": "u1F6B0.layer3",
          "order": 3
        }
      ]
    }
  },
  {
    "icon": {
      "glyph": {
        "code": "u1F6B1",
        "name": "nonpotablewatersymbol"
      },
      "layers": [
        {
          "color": "2B3B47",
          "name": "u1F6B1.layer1",
          "order": 1
        },
        {
          "color": "2B3B47",
          "name": "u1F6B1.layer2",
          "order": 2
        },
        {
          "color": "FF473E",
          "name": "u1F6B1.layer3",
          "order": 3
        }
      ]
    }
  },
  {
    "icon": {
      "glyph": {
        "code": "u1F6B7",
        "name": "nopedestrians"
      },
      "layers": [
        {
          "color": "2B3B47",
          "name": "u1F6B7.layer1",
          "order": 1
        },
        {
          "color": "FF473E",
          "name": "u1F6B7.layer2",
          "order": 2
        }
      ]
    }
  },
  {
    "icon": {
      "glyph": {
        "code": "u1F3E7",
        "name": "automatedtellermachine"
      },
      "layers": [
        {
          "color": "00B1FF",
          "name": "u1F3E7.layer1",
          "order": 1
        },
        {
          "color": "0096D1",
          "name": "u1F3E7.layer2",
          "order": 2
        },
        {
          "color": "0074A8",
          "name": "u1F3E7.layer3",
          "order": 3
        },
        {
          "color": "FFFFFF",
          "name": "u1F3E7.layer4",
          "order": 4
        },
        {
          "color": "FFFFFF",
          "name": "u1F3E7.layer5",
          "order": 5
        },
        {
          "color": "FFFFFF",
          "name": "u1F3E7.layer6",
          "order": 6
        }
      ]
    }
  },
  {
    "icon": {
      "glyph": {
        "code": "u2B55",
        "name": "heavylargecircle"
      },
      "layers": [
        {
          "color": "FF473E",
          "name": "u2B55.layer1",
          "order": 1
        }
      ]
    }
  },
  {
    "icon": {
      "glyph": {
        "code": "u27A1",
        "name": "blackrightwardsarrow"
      },
      "layers": [
        {
          "color": "597B91",
          "name": "u27A1.layer1",
          "order": 1
        },
        {
          "color": "2B5770",
          "name": "u27A1.layer2",
          "order": 2
        },
        {
          "color": "F9F9F7",
          "name": "u27A1.layer3",
          "order": 3
        }
      ]
    }
  },
  {
    "icon": {
      "glyph": {
        "code": "u1F3A6",
        "name": "cinema"
      },
      "layers": [
        {
          "color": "597B91",
          "name": "u1F3A6.layer1",
          "order": 1
        },
        {
          "color": "2B5770",
          "name": "u1F3A6.layer2",
          "order": 2
        },
        {
          "color": "FFFFFF",
          "name": "u1F3A6.layer3",
          "order": 3
        }
      ]
    }
  },
  {
    "icon": {
      "glyph": {
        "code": "u2B1B",
        "name": "blacklargesquare"
      },
      "layers": [
        {
          "color": "132028",
          "name": "u2B1B.layer1",
          "order": 1
        }
      ]
    }
  },
  {
    "icon": {
      "glyph": {
        "code": "u1F6AB",
        "name": "noentrysign"
      },
      "layers": [
        {
          "color": "FF473E",
          "name": "u1F6AB.layer1",
          "order": 1
        }
      ]
    }
  },
  {
    "icon": {
      "glyph": {
        "code": "u1F6B8",
        "name": "childrencrossing"
      },
      "layers": [
        {
          "color": "FFB636",
          "name": "u1F6B8.layer1",
          "order": 1
        },
        {
          "color": "2B3B47",
          "name": "u1F6B8.layer2",
          "order": 2
        },
        {
          "color": "2B3B47",
          "name": "u1F6B8.layer3",
          "order": 3
        }
      ]
    }
  },
  {
    "icon": {
      "glyph": {
        "code": "u1F6BB",
        "name": "restroom"
      },
      "layers": [
        {
          "color": "597B91",
          "name": "u1F6BB.layer1",
          "order": 1
        },
        {
          "color": "2B5770",
          "name": "u1F6BB.layer2",
          "order": 2
        },
        {
          "color": "FFFFFF",
          "name": "u1F6BB.layer3",
          "order": 3
        }
      ]
    }
  },
  {
    "icon": {
      "glyph": {
        "code": "u1F6BC",
        "name": "babysymbol"
      },
      "layers": [
        {
          "color": "FFB636",
          "name": "u1F6BC.layer1",
          "order": 1
        },
        {
          "color": "ED9B43",
          "name": "u1F6BC.layer2",
          "order": 2
        },
        {
          "color": "FFFFFF",
          "name": "u1F6BC.layer3",
          "order": 3
        }
      ]
    }
  },
  {
    "icon": {
      "glyph": {
        "code": "u1F6BA",
        "name": "womenssymbol"
      },
      "layers": [
        {
          "color": "FF5FD2",
          "name": "u1F6BA.layer1",
          "order": 1
        },
        {
          "color": "EF2EC2",
          "name": "u1F6BA.layer2",
          "order": 2
        },
        {
          "color": "FFFFFF",
          "name": "u1F6BA.layer3",
          "order": 3
        }
      ]
    }
  },
  {
    "icon": {
      "glyph": {
        "code": "u00A9",
        "name": "copyrightsign"
      },
      "layers": [
        {
          "color": "2B3B47",
          "name": "u00A9.layer1",
          "order": 1
        },
        {
          "color": "2B3B47",
          "name": "u00A9.layer2",
          "order": 2
        }
      ]
    }
  },
  {
    "icon": {
      "glyph": {
        "code": "u1F6BE",
        "name": "watercloset"
      },
      "layers": [
        {
          "color": "597B91",
          "name": "u1F6BE.layer1",
          "order": 1
        },
        {
          "color": "2B5770",
          "name": "u1F6BE.layer2",
          "order": 2
        },
        {
          "color": "FFFFFF",
          "name": "u1F6BE.layer3",
          "order": 3
        },
        {
          "color": "FFFFFF",
          "name": "u1F6BE.layer4",
          "order": 4
        }
      ]
    }
  },
  {
    "icon": {
      "glyph": {
        "code": "u1F4F4",
        "name": "mobilephoneoff"
      },
      "layers": [
        {
          "color": "FFB636",
          "name": "u1F4F4.layer1",
          "order": 1
        },
        {
          "color": "ED9B43",
          "name": "u1F4F4.layer2",
          "order": 2
        },
        {
          "color": "FFFFFF",
          "name": "u1F4F4.layer3",
          "order": 3
        },
        {
          "color": "FFB636",
          "name": "u1F4F4.layer4",
          "order": 4
        },
        {
          "color": "FFFFFF",
          "name": "u1F4F4.layer5",
          "order": 5
        },
        {
          "color": "FFFFFF",
          "name": "u1F4F4.layer6",
          "order": 6
        },
        {
          "color": "FFFFFF",
          "name": "u1F4F4.layer7",
          "order": 7
        }
      ]
    }
  },
  {
    "icon": {
      "glyph": {
        "code": "u1F4A0",
        "name": "diamondshapewithdotinside"
      },
      "layers": [
        {
          "color": "59CAFC",
          "name": "u1F4A0.layer1",
          "order": 1
        },
        {
          "color": "0096D1",
          "name": "u1F4A0.layer2",
          "order": 2
        }
      ]
    }
  },
  {
    "icon": {
      "glyph": {
        "code": "u2B1C",
        "name": "whitelargesquare"
      },
      "layers": [
        {
          "color": "D9DDE8",
          "name": "u2B1C.layer1",
          "order": 1
        }
      ]
    }
  },
  {
    "icon": {
      "glyph": {
        "code": "u1F6C3",
        "name": "customs"
      },
      "layers": [
        {
          "color": "597B91",
          "name": "u1F6C3.layer1",
          "order": 1
        },
        {
          "color": "2B5770",
          "name": "u1F6C3.layer2",
          "order": 2
        },
        {
          "color": "FFFFFF",
          "name": "u1F6C3.layer3",
          "order": 3
        },
        {
          "color": "FFFFFF",
          "name": "u1F6C3.layer4",
          "order": 4
        },
        {
          "color": "597B91",
          "name": "u1F6C3.layer5",
          "order": 5
        },
        {
          "color": "FFFFFF",
          "name": "u1F6C3.layer6",
          "order": 6
        },
        {
          "color": "597B91",
          "name": "u1F6C3.layer7",
          "order": 7
        },
        {
          "color": "FFFFFF",
          "name": "u1F6C3.layer8",
          "order": 8
        },
        {
          "color": "FFFFFF",
          "name": "u1F6C3.layer9",
          "order": 9
        }
      ]
    }
  },
  {
    "icon": {
      "glyph": {
        "code": "u1F6C2",
        "name": "passportcontrol"
      },
      "layers": [
        {
          "color": "597B91",
          "name": "u1F6C2.layer1",
          "order": 1
        },
        {
          "color": "2B5770",
          "name": "u1F6C2.layer2",
          "order": 2
        },
        {
          "color": "FFFFFF",
          "name": "u1F6C2.layer3",
          "order": 3
        },
        {
          "color": "FFFFFF",
          "name": "u1F6C2.layer4",
          "order": 4
        },
        {
          "color": "FFFFFF",
          "name": "u1F6C2.layer5",
          "order": 5
        },
        {
          "color": "597B91",
          "name": "u1F6C2.layer6",
          "order": 6
        },
        {
          "color": "FFFFFF",
          "name": "u1F6C2.layer7",
          "order": 7
        },
        {
          "color": "597B91",
          "name": "u1F6C2.layer8",
          "order": 8
        },
        {
          "color": "FFFFFF",
          "name": "u1F6C2.layer9",
          "order": 9
        },
        {
          "color": "597B91",
          "name": "u1F6C2.layer10",
          "order": 10
        }
      ]
    }
  },
  {
    "icon": {
      "glyph": {
        "code": "u1F6C5",
        "name": "leftluggage"
      },
      "layers": [
        {
          "color": "00B1FF",
          "name": "u1F6C5.layer1",
          "order": 1
        },
        {
          "color": "0096D1",
          "name": "u1F6C5.layer2",
          "order": 2
        },
        {
          "color": "FFFFFF",
          "name": "u1F6C5.layer3",
          "order": 3
        },
        {
          "color": "00B1FF",
          "name": "u1F6C5.layer4",
          "order": 4
        },
        {
          "color": "00B1FF",
          "name": "u1F6C5.layer5",
          "order": 5
        },
        {
          "color": "FFFFFF",
          "name": "u1F6C5.layer6",
          "order": 6
        },
        {
          "color": "FFFFFF",
          "name": "u1F6C5.layer7",
          "order": 7
        },
        {
          "color": "00B1FF",
          "name": "u1F6C5.layer8",
          "order": 8
        }
      ]
    }
  },
  {
    "icon": {
      "glyph": {
        "code": "u1F6C4",
        "name": "baggageclaim"
      },
      "layers": [
        {
          "color": "00B1FF",
          "name": "u1F6C4.layer1",
          "order": 1
        },
        {
          "color": "0096D1",
          "name": "u1F6C4.layer2",
          "order": 2
        },
        {
          "color": "FFFFFF",
          "name": "u1F6C4.layer3",
          "order": 3
        },
        {
          "color": "FFFFFF",
          "name": "u1F6C4.layer4",
          "order": 4
        }
      ]
    }
  },
  {
    "icon": {
      "glyph": {
        "code": "u26AB",
        "name": "mediumblackcircle"
      },
      "layers": [
        {
          "color": "132028",
          "name": "u26AB.layer1",
          "order": 1
        }
      ]
    }
  },
  {
    "icon": {
      "glyph": {
        "code": "u1F6B3",
        "name": "nobicycles"
      },
      "layers": [
        {
          "color": "2B3B47",
          "name": "u1F6B3.layer1",
          "order": 1
        },
        {
          "color": "FF473E",
          "name": "u1F6B3.layer2",
          "order": 2
        }
      ]
    }
  },
  {
    "icon": {
      "glyph": {
        "code": "u274C",
        "name": "crossmark"
      },
      "layers": [
        {
          "color": "FF473E",
          "name": "u274C.layer1",
          "order": 1
        }
      ]
    }
  }
]